idem_solaris/conf.py
idem_solaris/version.py
idem_solaris/exec/solaris/init.py
idem_solaris/exec/solaris/smbios.py
idem_solaris/exec/solaris/contracts/smbios.py
idem_solaris/grains/solaris/defaults.py
idem_solaris/grains/solaris/init.py
idem_solaris/grains/solaris/hw/bios.py
idem_solaris/grains/solaris/hw/cpu.py
idem_solaris/grains/solaris/hw/gpu.py
idem_solaris/grains/solaris/hw/mem.py
idem_solaris/grains/solaris/hw/slices.py
idem_solaris/grains/solaris/net/gateway.py
idem_solaris/grains/solaris/net/interfaces.py
idem_solaris/grains/solaris/os/arch.py
idem_solaris/grains/solaris/os/os.py
idem_solaris/states/solaris/init.py
idem_solaris-4.2.dist-info/LICENSE
idem_solaris-4.2.dist-info/METADATA
idem_solaris-4.2.dist-info/WHEEL
idem_solaris-4.2.dist-info/top_level.txt
idem_solaris-4.2.dist-info/RECORD
